stopwordsiso/__init__.py
stopwordsiso/_core.py
stopwordsiso/stopwords-iso.json
stopwordsiso-0.6.1.dist-info/METADATA
stopwordsiso-0.6.1.dist-info/WHEEL
stopwordsiso-0.6.1.dist-info/top_level.txt
stopwordsiso-0.6.1.dist-info/RECORD
