Metadata-Version: 2.1
Name: stopwordsiso
Version: 0.6.1
Summary: Collection of stopwords for multiple languages. Using ISO 639-1 language code.
Home-page: https://github.com/bact/stopwords-iso
Author: Arthit Suriyawongkul
Author-email: arthit@gmail.com
License: MIT
Keywords: stopwords language
Platform: UNKNOWN
Classifier: Development Status :: 3 - Alpha
Classifier: License :: OSI Approved :: MIT License
Classifier: Programming Language :: Python :: 3.6
Classifier: Topic :: Text Processing :: Linguistic
